README.rst
setup.py
YtApi/__init__.py
YtApi.egg-info/PKG-INFO
YtApi.egg-info/SOURCES.txt
YtApi.egg-info/dependency_links.txt
YtApi.egg-info/requires.txt
YtApi.egg-info/top_level.txt