Metadata-Version: 1.1
Name: YtApi
Version: 0.4
Summary: Api to download Youtube videos as mp3 files
Home-page: https://dadard.fr:8010/dadard/YtApi.git
Author: Florian Charpentier
Author-email: florian.charpentier@epita.fr
License: WTFPL
Platform: UNKNOWN
Classifier: Environment :: Web Environment
Classifier: Framework :: Flask
Classifier: Intended Audience :: Developers
Classifier: License :: Freeware
Classifier: Operating System :: OS Independent
Classifier: Programming Language :: Python
Classifier: Programming Language :: Python :: 3.6
Classifier: Topic :: Internet :: WWW/HTTP
Classifier: Topic :: Internet :: WWW/HTTP :: Dynamic Content
